imolecule/__init__.py
imolecule/format_converter.py
imolecule/json_formatter.py
imolecule/notebook.py
imolecule/viewer.template
imolecule/js/CanvasRenderer.js
imolecule/js/Projector.js
imolecule/js/ShaderToon.js
imolecule/js/TrackballControls.js
imolecule/js/__init__.py
imolecule/js/imolecule.js
imolecule/js/jquery-1.11.1.min.js
imolecule/js/jquery-ui.resizable.js
imolecule/js/three.min.js
imolecule/js/build/imolecule.min.js
imolecule/server/__init__.py
imolecule/server/server.py
imolecule/server/server.template
imolecule/server/css/avgrund.css
imolecule/server/css/chosen-sprite.png
imolecule/server/css/chosen-sprite@2x.png
imolecule/server/css/chosen.css
imolecule/server/css/server.css
imolecule/server/data/caffeine.json
imolecule/server/data/openbabel_formats.json
imolecule/server/js/FileSaver.min.js
imolecule/server/js/avgrund.js
imolecule/server/js/chosen.jquery.min.js
imolecule/server/js/imolecule.min.js
imolecule/server/js/jquery.min.js
imolecule/server/js/main.js
imolecule-0.2.2.dist-info/LICENSE.txt
imolecule-0.2.2.dist-info/METADATA
imolecule-0.2.2.dist-info/WHEEL
imolecule-0.2.2.dist-info/entry_points.txt
imolecule-0.2.2.dist-info/top_level.txt
imolecule-0.2.2.dist-info/RECORD
