Metadata-Version: 2.1
Name: imolecule
Version: 0.2.2
Summary: View molecules in the IPython notebook.
Home-page: http://github.com/patrickfuller/imolecule/
Author: Patrick Fuller
Author-email: patrickfuller@gmail.com
License: MIT
Platform: UNKNOWN
Classifier: Development Status :: 4 - Beta
Classifier: Intended Audience :: Education
Classifier: Natural Language :: English
Classifier: License :: OSI Approved :: MIT License
Classifier: Operating System :: OS Independent
Classifier: Programming Language :: Python
Classifier: Programming Language :: Python :: 3
Classifier: Programming Language :: Python :: 3.6
Classifier: Framework :: IPython
Classifier: Topic :: Education :: Computer Aided Instruction (CAI)
Classifier: Topic :: Scientific/Engineering :: Bio-Informatics
Classifier: Topic :: Scientific/Engineering :: Chemistry
Classifier: Topic :: Scientific/Engineering :: Visualization
License-File: LICENSE.txt
Requires-Dist: ipython
Requires-Dist: tornado
